HtmlTestRunner/.DS_Store
HtmlTestRunner/__init__.py
HtmlTestRunner/result.py
HtmlTestRunner/runner.py
HtmlTestRunner_Ably-1.0.2.dist-info/AUTHORS.md
HtmlTestRunner_Ably-1.0.2.dist-info/LICENSE
HtmlTestRunner_Ably-1.0.2.dist-info/METADATA
HtmlTestRunner_Ably-1.0.2.dist-info/WHEEL
HtmlTestRunner_Ably-1.0.2.dist-info/top_level.txt
HtmlTestRunner_Ably-1.0.2.dist-info/RECORD
